subprocconout/README.MD
subprocconout/__init__.py
subprocconout/requirements.txt
subprocconout/thirdparty.json
subprocconout-0.10.dist-info/LICENSE.rst
subprocconout-0.10.dist-info/METADATA
subprocconout-0.10.dist-info/WHEEL
subprocconout-0.10.dist-info/top_level.txt
subprocconout-0.10.dist-info/RECORD
