Metadata-Version: 2.1
Name: subprocconout
Version: 0.10
Summary: run a subprocess and capture its CONOUT$ console output
Home-page: https://github.com/hansalemaos/subprocconout
Author: Johannes Fischer
Author-email: aulasparticularesdealemaosp@gmail.com
License: MIT
Keywords: CONOUT,capture
Classifier: Development Status :: 4 - Beta
Classifier: Programming Language :: Python :: 3 :: Only
Classifier: Programming Language :: Python :: 3.10
Classifier: Topic :: Software Development :: Libraries :: Python Modules
Classifier: Topic :: Utilities
License-File: LICENSE.rst
